aio_quakeml_ingv_centro_nazionale_terremoti_client/__init__.py
aio_quakeml_ingv_centro_nazionale_terremoti_client/__version__.py
aio_quakeml_ingv_centro_nazionale_terremoti_client/consts.py
aio_quakeml_ingv_centro_nazionale_terremoti_client/feed.py
aio_quakeml_ingv_centro_nazionale_terremoti_client/feed_entry.py
aio_quakeml_ingv_centro_nazionale_terremoti_client/feed_manager.py
aio_quakeml_ingv_centro_nazionale_terremoti_client-0.4.dist-info/LICENSE
aio_quakeml_ingv_centro_nazionale_terremoti_client-0.4.dist-info/METADATA
aio_quakeml_ingv_centro_nazionale_terremoti_client-0.4.dist-info/WHEEL
aio_quakeml_ingv_centro_nazionale_terremoti_client-0.4.dist-info/top_level.txt
aio_quakeml_ingv_centro_nazionale_terremoti_client-0.4.dist-info/RECORD
